<?xml version="1.0"?><Applications><Application><enableAddDocument>false</enableAddDocument><enableCustomSort>false</enableCustomSort><SortOrder>D</SortOrder><CabinetName>orient_uat</CabinetName><Application-Name>ITCapitalGoods</Application-Name><UserName>supervisor</UserName><Time-Slice>5000</Time-Slice><loginOption>UserName</loginOption><ExtLoginOption>NormalLogin</ExtLoginOption><strMethodName> </strMethodName><EditAnnotationOption>true</EditAnnotationOption><enableVersion>false</enableVersion><enableDownload>false</enableDownload><MenuBar>true</MenuBar><Show-Document-Property-Link-Alist>false</Show-Document-Property-Link-Alist><restrictOption>Restrict</restrictOption><BatchSize>5</BatchSize><ViewDocument>N</ViewDocument><IntegrationType>Folder View</IntegrationType><UserPassword>:X-D;U:T-C;P-C;p5-C;b:d:u:SJDE</UserPassword><Show-Document-Property-Link>N</Show-Document-Property-Link><DisplayType>L</DisplayType><WinSize>FitToWidth</WinSize><Encrypted-Fields>IP,RNO</Encrypted-Fields><additionalDocDataclass>&lt;None&gt;</additionalDocDataclass><SiteId>1</SiteId><ObjectFlag>F</ObjectFlag><AnnotationDisplay>true</AnnotationDisplay><additionalDocNameList>&lt;None&gt;</additionalDocNameList><ServerIPs> </ServerIPs><Comments>ITCapitalGoods</Comments><configType>Basic</configType><PrintEnable>true</PrintEnable><ToolBarFlag>true</ToolBarFlag><OrderBy>5</OrderBy><TotalNoOfRecordToFetch>50</TotalNoOfRecordToFetch><ViewListDocument>N</ViewListDocument><dataBaseType>mssql</dataBaseType><Title>Folder View</Title><jtsPort>3333</jtsPort><jtsIp>192.168.10.58</jtsIp><OpenFileOption>true</OpenFileOption><strClassName> </strClassName><SearchOption>Data Class</SearchOption><Encryption-Enabled>false</Encryption-Enabled><TimeOut>500</TimeOut></Application><Application><enableAddDocument>false</enableAddDocument><EnableDCInfo>false</EnableDCInfo><enableCustomSort>false</enableCustomSort><SortOrder>D</SortOrder><CabinetName>orient_uat</CabinetName><Application-Name>FolderName</Application-Name><UserName>supervisor</UserName><Time-Slice>5000</Time-Slice><loginOption>UserName</loginOption><ExtLoginOption>NormalLogin</ExtLoginOption><strMethodName> </strMethodName><EditAnnotationOption>true</EditAnnotationOption><enableVersion>false</enableVersion><enableDownload>false</enableDownload><MenuBar>true</MenuBar><Show-Document-Property-Link-Alist>false</Show-Document-Property-Link-Alist><restrictOption>Restrict</restrictOption><BatchSize>5</BatchSize><ViewDocument>N</ViewDocument><IntegrationType>Folder View</IntegrationType><UserPassword>:X-D;U:T-C;P-C;p5-C;b:d:u:SJDE</UserPassword><Show-Document-Property-Link>N</Show-Document-Property-Link><DisplayType>L</DisplayType><WinSize>FitToWidth</WinSize><Encrypted-Fields>IP,RNO</Encrypted-Fields><additionalDocDataclass>&lt;None&gt;</additionalDocDataclass><SiteId>1</SiteId><ObjectFlag>F</ObjectFlag><AnnotationDisplay>true</AnnotationDisplay><additionalDocNameList>&lt;None&gt;</additionalDocNameList><ServerIPs> </ServerIPs><Comments>Folder</Comments><configType>Basic</configType><PrintEnable>true</PrintEnable><ToolBarFlag>true</ToolBarFlag><OrderBy>5</OrderBy><TotalNoOfRecordToFetch>50</TotalNoOfRecordToFetch><ViewListDocument>N</ViewListDocument><dataBaseType>oracle</dataBaseType><Title>Try IT</Title><jtsPort>3333</jtsPort><jtsIp>192.168.10.58</jtsIp><OpenFileOption>true</OpenFileOption><strClassName> </strClassName><SearchOption>Object</SearchOption><Encryption-Enabled>false</Encryption-Enabled><TimeOut>500</TimeOut></Application><Application><enableAddDocument>false</enableAddDocument><enableCustomSort>false</enableCustomSort><SortOrder>D</SortOrder><CabinetName>orient_uat</CabinetName><Application-Name>ImageEnablement</Application-Name><UserName>supervisor</UserName><Time-Slice>5000</Time-Slice><loginOption>UserName</loginOption><ExtLoginOption>NormalLogin</ExtLoginOption><strMethodName> </strMethodName><EditAnnotationOption>true</EditAnnotationOption><enableVersion>false</enableVersion><enableDownload>true</enableDownload><MenuBar>true</MenuBar><Show-Document-Property-Link-Alist>false</Show-Document-Property-Link-Alist><restrictOption>Allow</restrictOption><BatchSize>5</BatchSize><ViewDocument>D</ViewDocument><IntegrationType>Document View</IntegrationType><UserPassword>:X-D;U:T-C;P-C;p5-C;b:d:u:SJDE</UserPassword><Show-Document-Property-Link>N</Show-Document-Property-Link><DisplayType>L</DisplayType><WinSize>FitToWidth</WinSize><Encrypted-Fields>IP,RNO</Encrypted-Fields><additionalDocDataclass>&lt;None&gt;</additionalDocDataclass><SiteId>1</SiteId><ObjectFlag>D</ObjectFlag><AnnotationDisplay>true</AnnotationDisplay><additionalDocNameList>&lt;None&gt;</additionalDocNameList><ServerIPs> </ServerIPs><Comments>ImageEnablement</Comments><configType>Basic</configType><PrintEnable>true</PrintEnable><ToolBarFlag>true</ToolBarFlag><OrderBy>5</OrderBy><TotalNoOfRecordToFetch>50</TotalNoOfRecordToFetch><ViewListDocument>L</ViewListDocument><dataBaseType>mssql</dataBaseType><Title>ImageEnablement</Title><jtsPort>3333</jtsPort><jtsIp>localhost</jtsIp><OpenFileOption>true</OpenFileOption><strClassName> </strClassName><SearchOption>Data Class</SearchOption><Encryption-Enabled>false</Encryption-Enabled><TimeOut>500</TimeOut></Application><Application><enableAddDocument>false</enableAddDocument><enableCustomSort>false</enableCustomSort><SortOrder>D</SortOrder><CabinetName>orient_uat</CabinetName><Application-Name>PHCC</Application-Name><UserName> </UserName><Time-Slice>5000</Time-Slice><loginOption>External_Login</loginOption><ExtLoginOption>NormalLogin</ExtLoginOption><strMethodName> </strMethodName><EditAnnotationOption>true</EditAnnotationOption><enableVersion>false</enableVersion><enableDownload>false</enableDownload><MenuBar>true</MenuBar><Show-Document-Property-Link-Alist>false</Show-Document-Property-Link-Alist><restrictOption>Restrict</restrictOption><BatchSize>5</BatchSize><ViewDocument>N</ViewDocument><IntegrationType>Document View</IntegrationType><UserPassword> </UserPassword><Show-Document-Property-Link>N</Show-Document-Property-Link><DisplayType>L</DisplayType><WinSize>FitToWidth</WinSize><Encrypted-Fields>IP,RNO</Encrypted-Fields><additionalDocDataclass>&lt;None&gt;</additionalDocDataclass><SiteId>1</SiteId><ObjectFlag>D</ObjectFlag><AnnotationDisplay>true</AnnotationDisplay><additionalDocNameList>&lt;None&gt;</additionalDocNameList><ServerIPs> </ServerIPs><Comments>This is system generated Web API.</Comments><configType>Basic</configType><PrintEnable>false</PrintEnable><ToolBarFlag>true</ToolBarFlag><OrderBy>5</OrderBy><TotalNoOfRecordToFetch>50</TotalNoOfRecordToFetch><ViewListDocument>N</ViewListDocument><dataBaseType>PHCC</dataBaseType><Title>PHCC</Title><jtsPort>8080</jtsPort><jtsIp>127.0.0.1</jtsIp><OpenFileOption>true</OpenFileOption><strClassName> </strClassName><SearchOption>Object</SearchOption><Encryption-Enabled>false</Encryption-Enabled><TimeOut>5000</TimeOut></Application></Applications>